stardist_stacked_timepoints/__init__.py
stardist_stacked_timepoints/config_2d.py
stardist_stacked_timepoints/data_2d.py
stardist_stacked_timepoints/data_base.py
stardist_stacked_timepoints/model_2d.py
stardist_stacked_timepoints/predict.py
stardist_stacked_timepoints/py.typed
stardist_stacked_timepoints/sample_patches.py
stardist_stacked_timepoints/utils.py
stardist_stacked_timepoints-0.1.0.dist-info/entry_points.txt
stardist_stacked_timepoints-0.1.0.dist-info/LICENSE
stardist_stacked_timepoints-0.1.0.dist-info/WHEEL
stardist_stacked_timepoints-0.1.0.dist-info/METADATA
stardist_stacked_timepoints-0.1.0.dist-info/RECORD
