Metadata-Version: 2.1
Name: stardist-stacked-timepoints
Version: 0.1.0
Summary: Stardist Stacked Timepoints
Home-page: https://github.com/gatoniel/stardist-stacked-timepoints
License: MIT
Author: Niklas Netter
Author-email: niknett@gmail.com
Requires-Python: >=3.8,<3.10
Classifier: Development Status :: 1 - Planning
Classifier: License :: OSI Approved :: MIT License
Classifier: Programming Language :: Python :: 3
Classifier: Programming Language :: Python :: 3.8
Classifier: Programming Language :: Python :: 3.9
Requires-Dist: edt (>=2.3.0,<3.0.0)
Requires-Dist: numba (>=0.56.4,<0.57.0)
Requires-Dist: numpy (>=1.20.0)
Requires-Dist: stardist (>=0.8.3,<0.9.0)
Project-URL: Changelog, https://github.com/gatoniel/stardist-stacked-timepoints/releases
Project-URL: Documentation, https://stardist-stacked-timepoints.readthedocs.io
Project-URL: Repository, https://github.com/gatoniel/stardist-stacked-timepoints
